buildtools/__init__.py
buildtools/_os_utils_linux.py
buildtools/_os_utils_win32.py
buildtools/as3.py
buildtools/bt_logging.py
buildtools/buildsystem/CCompiler.py
buildtools/buildsystem/__init__.py
buildtools/buildsystem/baseproject.py
buildtools/buildsystem/gcc.py
buildtools/buildsystem/msbuild.py
buildtools/buildsystem/prebuild.py
buildtools/buildsystem/visualstudio.py
buildtools/cli/__init__.py
buildtools/cli/nuitka_plus/README.md
buildtools/cli/nuitka_plus/__init__.py
buildtools/cli/nuitka_plus/__main__.py
buildtools/cli.py
buildtools/config.py
buildtools/consts.py
buildtools/error.py
buildtools/ext/__init__.py
buildtools/ext/salt/__init__.py
buildtools/ext/salt/jinja_ext.py
buildtools/http.py
buildtools/indentation.py
buildtools/lxml_utils.py
buildtools/maestro/__init__.py
buildtools/maestro/base_target.py
buildtools/maestro/coffeescript.py
buildtools/maestro/convert_data.py
buildtools/maestro/docs.py
buildtools/maestro/enumwriters/__init__.py
buildtools/maestro/enumwriters/coffee.py
buildtools/maestro/enumwriters/enumwriter.py
buildtools/maestro/enumwriters/php.py
buildtools/maestro/enumwriters/python.py
buildtools/maestro/enumwriters/types.py
buildtools/maestro/fileio.py
buildtools/maestro/genenum.py
buildtools/maestro/git.py
buildtools/maestro/jinja2.py
buildtools/maestro/nuitka.py
buildtools/maestro/package_managers.py
buildtools/maestro/shell.py
buildtools/maestro/utils.py
buildtools/maestro/web.py
buildtools/os_utils.py
buildtools/paths.py
buildtools/posix/__init__.py
buildtools/posix/elf.py
buildtools/pygit2_callbacks.py
buildtools/qconfig5.py
buildtools/repo/__init__.py
buildtools/repo/base.py
buildtools/repo/git.py
buildtools/repo/hg.py
buildtools/timing.py
buildtools/twisted_utils.py
buildtools/types.py
buildtools/utils.py
buildtools/wrapper/__init__.py
buildtools/wrapper/ant.py
buildtools/wrapper/ccache.py
buildtools/wrapper/cmake.py
buildtools/wrapper/cotire.py
buildtools/wrapper/distcc.py
buildtools/wrapper/fpm.py
buildtools/wrapper/git.py
pybuildtools-0.7.8.dist-info/METADATA
pybuildtools-0.7.8.dist-info/WHEEL
pybuildtools-0.7.8.dist-info/licenses/LICENSE
pybuildtools-0.7.8.dist-info/RECORD
