Metadata-Version: 2.4
Name: pybuildtools
Version: 0.7.8
Summary: A set of tools for putting together buildscripts and other CLI applications
License-Expression: MIT
License-File: LICENSE
Author: Rob Nelson
Author-email: nexisentertainment@gmail.com
Requires-Python: >=3.12,<4.0
Classifier: Programming Language :: Python :: 3 :: Only
Classifier: Programming Language :: Python :: 3.13
Classifier: Programming Language :: Python :: 3.14
Provides-Extra: all
Provides-Extra: nuitka
Provides-Extra: pygit2
Provides-Extra: twisted
Requires-Dist: colorama (>=0.4.6,<0.5.0)
Requires-Dist: jinja2 (>=3.1.6,<4.0.0)
Requires-Dist: lxml (>=6.0.2,<7)
Requires-Dist: markupsafe (>=3.0.3,<4)
Requires-Dist: nuitka (>=2.8.9,<3) ; extra == "all"
Requires-Dist: nuitka (>=2.8.9,<3) ; extra == "nuitka"
Requires-Dist: psutil (>=7.1.3,<8)
Requires-Dist: pygit2 (>=1.19,<2) ; extra == "all"
Requires-Dist: pygit2 (>=1.19,<2) ; extra == "pygit2"
Requires-Dist: requests (>=2.32.5,<3)
Requires-Dist: ruamel-yaml (>=0.18.16,<0.19.0)
Requires-Dist: six (>=1.17,<2)
Requires-Dist: subprocess-tee (>=0.4.2,<0.5.0)
Requires-Dist: toml (>=0.10.2,<0.11.0)
Requires-Dist: tqdm (>=4.67.1,<5)
Requires-Dist: twisted (>=25.5,<26) ; extra == "all"
Requires-Dist: twisted (>=25.5,<26) ; extra == "twisted"
Project-URL: Homepage, https://gitlab.com/N3X15/python-build-tools
Project-URL: Repository, https://gitlab.com/N3X15/python-build-tools.git
